{
  "systemName": "QUANT-X Global Securities Directory",
  "version": "1.82",
  "lastUpdated": "2026-07-07T20:29:00Z",
  "sectors": [
    "Technology",
    "Biotech",
    "Financials",
    "Energy",
    "Defense",
    "Consumer"
  ],
  "companies": {
    "Technology": [
      { "sym": "NVA", "name": "Nova Quantum Grid", "basePrice": 45.50, "description": "High-throughput cloud quantum networks." },
      { "sym": "HXG", "name": "Helix Cybernetics", "basePrice": 124.20, "description": "Bio-cybernetic sensory components and logic chips." },
      { "sym": "ZNT", "name": "Zenith Microchips", "basePrice": 88.00, "description": "Next-gen ultra-dense semiconductor wafers." },
      { "sym": "STR", "name": "Stratus Cloud Net", "basePrice": 32.10, "description": "Decentralized serverless routing mesh networks." },
      { "sym": "QNT", "name": "Quantum Core Sys", "basePrice": 142.75, "description": "Physical qubit storage containers and cryogenic modules." },
      { "sym": "VTX", "name": "Vertex Holograms", "basePrice": 18.50, "description": "Dynamic structural light arrays and optical projection systems." },
      { "sym": "INF", "name": "Infinity Cryptos", "basePrice": 5.40, "description": "Zero-knowledge decentralized blockchain ledgers." }
    ],
    "Biotech": [
      { "sym": "ATH", "name": "Aether NeuroGen", "basePrice": 95.00, "description": "Optogenetic neuro-stimulation treatments." },
      { "sym": "GLX", "name": "Galaxy Therapeutics", "basePrice": 62.40, "description": "Targeted synthetic enzyme therapeutic models." },
      { "sym": "VIR", "name": "ViroTech Synths", "basePrice": 112.10, "description": "Biomimetic adaptive cellular antiviral design." },
      { "sym": "GEN", "name": "Genesis Organics", "basePrice": 39.90, "description": "Lab-grown structural biopolymers and cellular materials." },
      { "sym": "BIO", "name": "Biocel Lab Inc.", "basePrice": 22.80, "description": "High-throughput diagnostic enzyme assay chips." }
    ],
    "Financials": [
      { "sym": "VNG", "name": "Vanguard Blockcap", "basePrice": 150.00, "description": "Algorithmic smart-contract asset clearing services." },
      { "sym": "KRS", "name": "Kairos Sovereign", "basePrice": 75.30, "description": "Direct cross-border decentralized digital settlements." },
      { "sym": "NOB", "name": "Noble Trust Capital", "basePrice": 118.00, "description": "Institutional smart collateral protection custody." },
      { "sym": "MRD", "name": "Meridian Liquidity", "basePrice": 44.20, "description": "High-speed automated liquidity routing pools." },
      { "sym": "APX", "name": "Apex Clearing Corp", "basePrice": 82.50, "description": "Next-generation cleared asset clearing mechanics." }
    ],
    "Energy": [
      { "sym": "FUS", "name": "Fusion Nuclear", "basePrice": 165.00, "description": "Commercial continuous magnetic confinement fusion reactors." },
      { "sym": "SOL", "name": "Solstice Solar Hub", "basePrice": 28.40, "description": "High-orbit solar array harvesting telemetry grids." },
      { "sym": "HYD", "name": "Hydrogen Energy", "basePrice": 35.10, "description": "Cryogenic liquid hydrogen distribution networks." },
      { "sym": "VOL", "name": "Voltaic Grid Co", "basePrice": 52.80, "description": "Superconducting smart municipal power load balancing." }
    ],
    "Defense": [
      { "sym": "TTN", "name": "Titan Armor Mech", "basePrice": 135.00, "description": "Heavy protective structural robotics and automated frames." },
      { "sym": "WRD", "name": "Warden Defense Net", "basePrice": 92.40, "description": "Automated regional airspace shield radar monitoring." },
      { "sym": "XEN", "name": "Xenon Laser Corp", "basePrice": 74.00, "description": "Optical fiber laser array emitters and defense matrices." },
      { "sym": "DRA", "name": "Draco Tactical", "basePrice": 48.60, "description": "Autonomous security drone chassis platforms." }
    ],
    "Consumer": [
      { "sym": "KRM", "name": "Karma Synthetic Foods", "basePrice": 15.20, "description": "Nutrient-dense synthetic crop growth complexes." },
      { "sym": "YAR", "name": "Yara VR Wear", "basePrice": 62.00, "description": "Lightweight virtual sensory apparel and haptic feedback." },
      { "sym": "VES", "name": "Vesper Luxury Air", "basePrice": 110.50, "description": "Electric vertical takeoff personal transport grids." },
      { "sym": "WIL", "name": "Willow Greenery", "basePrice": 24.15, "description": "Indoor air filtration urban micro-botanical biomes." }
    ]
  }
}